hydrotools/svi_client/__init__.py
hydrotools/svi_client/_version.py
hydrotools/svi_client/clients.py
hydrotools/svi_client/consts.py
hydrotools/svi_client/url_builders.py
hydrotools/svi_client/types/__init__.py
hydrotools/svi_client/types/field_name_map.py
hydrotools/svi_client/types/type_definitions.py
hydrotools/svi_client/types/utilities.py
hydrotools_svi_client-1.1.0.dist-info/licenses/LICENSE
hydrotools_svi_client-1.1.0.dist-info/licenses/NOTICE
hydrotools_svi_client-1.1.0.dist-info/METADATA
hydrotools_svi_client-1.1.0.dist-info/WHEEL
hydrotools_svi_client-1.1.0.dist-info/top_level.txt
hydrotools_svi_client-1.1.0.dist-info/RECORD
