Metadata-Version: 2.4
Name: hydrotools.svi_client
Version: 1.1.0
Summary: Retrieve Social Vulnerability Index data from The Center for Disease Control / The Agency for Toxic Substances and Disease Registry.
Author-email: Austin Raney <aaraney@protonmail.com>
License: 
Project-URL: Homepage, https://github.com/NOAA-OWP/hydrotools
Project-URL: Documentation, https://noaa-owp.github.io/hydrotools/hydrotools.svi_client.html
Project-URL: Repository, https://github.com/NOAA-OWP/hydrotools/tree/main/python/svi_client
Project-URL: Bug Tracker, https://github.com/NOAA-OWP/hydrotools/issues
Classifier: Development Status :: 5 - Production/Stable
Classifier: Intended Audience :: Education
Classifier: Intended Audience :: Science/Research
Classifier: License :: OSI Approved :: Apache Software License
Classifier: Programming Language :: Python :: 3.9
Classifier: Programming Language :: Python :: 3.10
Classifier: Programming Language :: Python :: 3.11
Classifier: Programming Language :: Python :: 3.12
Classifier: Topic :: Scientific/Engineering :: Hydrology
Classifier: Operating System :: OS Independent
Requires-Python: >=3.9
License-File: LICENSE
License-File: NOTICE
Requires-Dist: hydrotools._restclient>=4.1.0
Requires-Dist: numpy>=1.20.0
Requires-Dist: pandas
Requires-Dist: geopandas
Requires-Dist: pydantic
Requires-Dist: typing_extensions
Provides-Extra: develop
Requires-Dist: pytest; extra == "develop"
Requires-Dist: pytest-aiohttp; extra == "develop"
Dynamic: license-file
